Workbook

Sheet Supuestos
A1: MisFinanzas — Supuestos de costos y precio
A2: Etapa 0, Día 1 · Celdas azules con fondo amarillo = editables. El resto se recalcula solo.
A4: Supuesto | B4: Valor | C4: Fuente / nota
A5: Precio mensual Premium (CLP) | B5: 3990 | C5: EDITAR: precio a validar en la Etapa 0, Días 2-3 (encuesta a 8-10 personas).
A6: Tipo de cambio USD/CLP | B6: 930 | C6: Referencial, mercado interbancario, agosto 2026. Fluctúa — ajustar antes de decisiones grandes.
A7: % comisión de tienda (Apple/Google) | B7: 0.15 | C7: Con el Programa para Pequeñas Empresas (Apple) y el tramo <US$1M/año (Google), ambos bajan la comisión de 30% a 15%. Requiere inscripción explícita en cada tienda, no es automático.
A8: Costo anual Apple Developer Program (USD) | B8: 99 | C8: Cifra oficial de Apple, 2026.
A9: Costo único Google Play Console (USD) | B9: 25 | C9: Pago único, sin renovación. Cifra oficial de Google, 2026.
A10: Límite gratuito Supabase (MAU) | B10: 50000 | C10: Plan gratuito: hasta 50.000 usuarios activos mensuales, 500 MB de base de datos, 1 GB de almacenamiento. El límite de almacenamiento puede llegar antes que el de MAU — revisar aparte.
A11: Costo mensual Supabase Pro si se supera (USD) | B11: 25 | C11: Plan Pro, 2026. Incluye crédito de cómputo; uso adicional se cobra aparte.
A12: Límite gratuito RevenueCat (MTR mensual, USD) | B12: 2500 | C12: Ingreso mensual rastreado (bruto, antes de comisión de tienda). Gratis hasta este monto.
A13: % RevenueCat sobre el MTR al superar el límite | B13: 0.01 | C13: 1% del MTR total una vez superado el umbral. Verificar en revenuecat.com/pricing antes de comprometerse — cambia con frecuencia.
A14: % de usuarios activos que se hacen Premium | B14: 0.05 | C14: Supuesto de conversión inicial — ajustar con datos reales después de la Etapa 2 (validación externa).
A16: Leyenda
A17: Azul + amarillo = celda para editar
A18: Negro = fórmula (no editar)
A19: Verde = referencia directa a otra pestaña

Sheet Escenarios de rentabilidad
A1: MisFinanzas — Escenarios de rentabilidad mensual
A2: Cambia 'Usuarios Premium' o el precio en Supuestos y todo se recalcula. La fila 'Tu escenario' es libre para probar tus propios números.
A4: Escenario | B4: Usuarios Premium | C4: % conversión (Supuestos) | D4: Usuarios activos totales (estim.) | E4: Ingreso bruto mensual (CLP) | F4: Ingreso bruto mensual (USD) | G4: Comisión tienda 15% (CLP) | H4: Ingreso neto de tienda (CLP) | I4: Costo RevenueCat mensual (USD) | J4: Costo Supabase mensual (USD) | K4: Utilidad mensual (CLP) | L4: Utilidad anual (CLP)
A5: Conservador | B5: 50 | C5: =Supuestos!$B$14 -> 0.05 | D5: =IFERROR(B5/C5,0) -> 1000 | E5: =B5*Supuestos!$B$5 -> 199500 | F5: =E5/Supuestos!$B$6 -> 214.51613 | G5: =E5*Supuestos!$B$7 -> 29925 | H5: =E5-G5 -> 169575 | I5: =IF(F5>Supuestos!$B$12,F5*Supuestos!$B$13,0) -> 0 | J5: =IF(D5>Supuestos!$B$10,Supuestos!$B$11,0) -> 0 | K5: =H5-(I5+J5+Supuestos!$B$8/12+Supuestos!$B$9/12)*Supuestos!$B$6 -> 159965 | L5: =K5*12 -> 1919580
A6: Intermedio | B6: 200 | C6: =Supuestos!$B$14 -> 0.05 | D6: =IFERROR(B6/C6,0) -> 4000 | E6: =B6*Supuestos!$B$5 -> 798000 | F6: =E6/Supuestos!$B$6 -> 858.06452 | G6: =E6*Supuestos!$B$7 -> 119700 | H6: =E6-G6 -> 678300 | I6: =IF(F6>Supuestos!$B$12,F6*Supuestos!$B$13,0) -> 0 | J6: =IF(D6>Supuestos!$B$10,Supuestos!$B$11,0) -> 0 | K6: =H6-(I6+J6+Supuestos!$B$8/12+Supuestos!$B$9/12)*Supuestos!$B$6 -> 668690 | L6: =K6*12 -> 8024280
A7: Optimista | B7: 500 | C7: =Supuestos!$B$14 -> 0.05 | D7: =IFERROR(B7/C7,0) -> 10000 | E7: =B7*Supuestos!$B$5 -> 1995000 | F7: =E7/Supuestos!$B$6 -> 2145.1613 | G7: =E7*Supuestos!$B$7 -> 299250 | H7: =E7-G7 -> 1695750 | I7: =IF(F7>Supuestos!$B$12,F7*Supuestos!$B$13,0) -> 0 | J7: =IF(D7>Supuestos!$B$10,Supuestos!$B$11,0) -> 0 | K7: =H7-(I7+J7+Supuestos!$B$8/12+Supuestos!$B$9/12)*Supuestos!$B$6 -> 1686140 | L7: =K7*12 -> 20233680
A8: Tu escenario | B8: 10 | C8: =Supuestos!$B$14 -> 0.05 | D8: =IFERROR(B8/C8,0) -> 200 | E8: =B8*Supuestos!$B$5 -> 39900 | F8: =E8/Supuestos!$B$6 -> 42.903226 | G8: =E8*Supuestos!$B$7 -> 5985 | H8: =E8-G8 -> 33915 | I8: =IF(F8>Supuestos!$B$12,F8*Supuestos!$B$13,0) -> 0 | J8: =IF(D8>Supuestos!$B$10,Supuestos!$B$11,0) -> 0 | K8: =H8-(I8+J8+Supuestos!$B$8/12+Supuestos!$B$9/12)*Supuestos!$B$6 -> 24305 | L8: =K8*12 -> 291660
A10: Nota
A11: La utilidad mensual resta comisión de tienda, RevenueCat, Supabase y el prorrateo mensual de las cuentas developer (Apple US$99/año + Google US$25 pago único, este último solo pesa el primer año). No incluye tu propio tiempo ni costos de marketing, que hoy son US$0 pero no serán US$0 para siempre.
